MANIFEST.in
README.rst
requirements.txt
setup.py
django_marcus.egg-info/PKG-INFO
django_marcus.egg-info/SOURCES.txt
django_marcus.egg-info/dependency_links.txt
django_marcus.egg-info/not-zip-safe
django_marcus.egg-info/requires.txt
django_marcus.egg-info/top_level.txt
marcus/__init__.py
marcus/actions.py
marcus/admin.py
marcus/apps.py
marcus/context_processors.py
marcus/feeds.py
marcus/forms.py
marcus/managers.py
marcus/models.py
marcus/queryset.py
marcus/sitemap_urls.py
marcus/sitemaps.py
marcus/urls.py
marcus/utils.py
marcus/views.py
marcus/widgets.py
marcus/locale/ru/LC_MESSAGES/django.mo
marcus/locale/ru/LC_MESSAGES/django.po
marcus/management/__init__.py
marcus/management/commands/__init__.py
marcus/management/commands/wordpress_importer.py
marcus/migrations/0001_initial.py
marcus/migrations/__init__.py
marcus/static/robots.txt
marcus/static/screen.css
marcus/static/highlight.js/LICENSE
marcus/static/highlight.js/README.md
marcus/static/highlight.js/README.ru.md
marcus/static/highlight.js/classref.txt
marcus/static/highlight.js/highlight.pack.js
marcus/static/highlight.js/styles/arta.css
marcus/static/highlight.js/styles/ascetic.css
marcus/static/highlight.js/styles/brown_paper.css
marcus/static/highlight.js/styles/brown_papersq.png
marcus/static/highlight.js/styles/dark.css
marcus/static/highlight.js/styles/default.css
marcus/static/highlight.js/styles/far.css
marcus/static/highlight.js/styles/github.css
marcus/static/highlight.js/styles/googlecode.css
marcus/static/highlight.js/styles/idea.css
marcus/static/highlight.js/styles/ir_black.css
marcus/static/highlight.js/styles/magula.css
marcus/static/highlight.js/styles/monokai.css
marcus/static/highlight.js/styles/pojoaque.css
marcus/static/highlight.js/styles/pojoaque.jpg
marcus/static/highlight.js/styles/school_book.css
marcus/static/highlight.js/styles/school_book.png
marcus/static/highlight.js/styles/solarized_dark.css
marcus/static/highlight.js/styles/solarized_light.css
marcus/static/highlight.js/styles/sunburst.css
marcus/static/highlight.js/styles/vs.css
marcus/static/highlight.js/styles/xcode.css
marcus/static/highlight.js/styles/zenburn.css
marcus/static/images/chevron-right.png
marcus/static/images/download.gif
