Metadata-Version: 1.1
Name: django-marcus
Version: 1.0.4
Summary: Bilingual blog on Django
Home-page: http://github.com/adw0rd/marcus
Author: Mikhail Andreev
Author-email: x11org@gmail.com
License: BSD
Keywords: django,blog
Platform: UNKNOWN
Classifier: Environment :: Web Environment
Classifier: Programming Language :: Python
Classifier: Framework :: Django
Classifier: License :: OSI Approved :: BSD License
Classifier: Topic :: Software Development :: Debuggers
Classifier: Topic :: Software Development :: Libraries :: Application Frameworks
Classifier: Topic :: Software Development :: Libraries :: Python Modules
